{
  "_readme": "Authoritative element assignments for all cards in cards.jsonl. Used by US-GM-005 so Ralph does not have to guess. Elements: blood, holy, arcane, shadow, nature. Reasons are brief justifications for each choice.",
  "assignments": {
    "zombie_i":               { "element": "blood",  "reason": "undead" },
    "skeleton_i":             { "element": "blood",  "reason": "undead" },
    "ghoul_i":                { "element": "blood",  "reason": "undead" },
    "vampire_spawn_i":        { "element": "blood",  "reason": "undead" },
    "revenant_i":             { "element": "blood",  "reason": "undead" },
    "strahd_i":               { "element": "blood",  "reason": "vampire lord; undead despite boss/ravenloft tags" },
    "strahd_ii":              { "element": "blood",  "reason": "vampire lord; undead despite boss/ravenloft tags" },
    "strahd_iii":             { "element": "blood",  "reason": "vampire lord; undead despite boss/ravenloft tags" },
    "blood_queen_ireena_i":   { "element": "blood",  "reason": "Blood Queen — name is self-evident" },
    "blood_queen_ireena_ii":  { "element": "blood",  "reason": "Blood Queen — name is self-evident" },
    "blood_queen_ireena_iii": { "element": "blood",  "reason": "Blood Queen — name is self-evident" },

    "swarm_of_bats_i":        { "element": "nature", "reason": "beast" },
    "dire_wolf_i":            { "element": "nature", "reason": "beast" },
    "needle_blight_i":        { "element": "nature", "reason": "plant creature" },
    "druid_of_yester_hill_i": { "element": "nature", "reason": "druid; corrupted but still nature-based" },
    "muck_lord_ii":           { "element": "nature", "reason": "legendary catoblepas — swamp beast" },
    "sven_stormbjorn_i":      { "element": "nature", "reason": "barbarian — primal warrior" },
    "sancho_ii":              { "element": "nature", "reason": "half-giant bruiser — raw physical/primal strength" },
    "davian_martikov_i":      { "element": "nature", "reason": "wereraven, Order of the Feather" },
    "adrian_martikov_i":      { "element": "nature", "reason": "wereraven, Order of the Feather" },
    "elvir_martikov_i":       { "element": "nature", "reason": "wereraven, Order of the Feather" },
    "urwin_martikov_i":       { "element": "nature", "reason": "wereraven, Order of the Feather" },
    "parriwimple_i":          { "element": "nature", "reason": "gentle giant, innocent/physical, no supernatural affiliation" },

    "howl_ii":                { "element": "holy",   "reason": "cleric tag" },
    "the_abbot_ii":           { "element": "holy",   "reason": "holy tag; fallen deva" },
    "sergei_spirit_i":        { "element": "holy",   "reason": "holy tag; restless spirit of a noble soul" },
    "argynvost_ii":           { "element": "holy",   "reason": "silver dragon ghost; radiant, noble, good-aligned" },
    "ismark_kolyana_i":       { "element": "holy",   "reason": "protective older brother; good-hearted defender" },
    "vivienne_kolyana_i":     { "element": "holy",   "reason": "normal noble; good-hearted Barovian, Kolyana family" },

    "animated_armor_i":       { "element": "arcane", "reason": "arcane construct" },
    "cinaed_ii":              { "element": "arcane", "reason": "sorcerer" },
    "mercucio_ii":            { "element": "arcane", "reason": "sorcerer" },
    "bryly_ii":               { "element": "arcane", "reason": "bard; uses arcane magic" },
    "merilion_i":             { "element": "arcane", "reason": "bard; uses arcane magic" },
    "blinsky_i":              { "element": "arcane", "reason": "toymaker; creates mechanical/magical constructs for Strahd" },
    "madam_eva_i":            { "element": "arcane", "reason": "Vistani tarokka seer; divination/arcane" },
    "kasimir_velikov_i":      { "element": "arcane", "reason": "dusk elf with wizard-type abilities" },
    "baba_lysaga_ii":         { "element": "arcane", "reason": "witch; powerful arcane spellcaster" },
    "vasilka_i":              { "element": "arcane", "reason": "flesh golem; construct created via arcane/divine means" },

    "scarecrow_i":            { "element": "shadow", "reason": "Strahd's dark animated construct; shadow magic" },
    "werewolf_i":             { "element": "shadow", "reason": "cursed shapeshifter; shadow-touched" },
    "brazen_bell_ii":         { "element": "shadow", "reason": "martial fighter (not divine); Devil Slayer" },
    "decibelus_ii":           { "element": "shadow", "reason": "Strahd's seneschal and bodyguard; in service of darkness" },
    "black_loretta_ii":       { "element": "shadow", "reason": "Red Knives gang leader; criminal/gunslinger" },
    "puck_ii":                { "element": "shadow", "reason": "Red Knives trickster; rogue/jester type" },
    "izek_strazni_i":         { "element": "shadow", "reason": "demonic arm; brutal enforcer; fiend-touched" },
    "baron_vargas_i":         { "element": "shadow", "reason": "oppressive Vallaki tyrant; rules through fear" },
    "lady_wachter_i":         { "element": "shadow", "reason": "Strahd cultist; communes with evil spirits" },
    "arrigal_i":              { "element": "shadow", "reason": "Vistani spy working for Strahd; assassin type" },
    "rahadin_ii":             { "element": "shadow", "reason": "Strahd's chamberlain; dusk elf assassin, psychic death shriek" },
    "morgantha_ii":           { "element": "shadow", "reason": "night hag; shadow magic" },
    "ezmerelda_ii":           { "element": "shadow", "reason": "monster hunter; operates in darkness and guile, not divine power" },
    "van_richten_ii":         { "element": "shadow", "reason": "monster hunter; scholar/spy, not a holy warrior" },
    "fatima_i":               { "element": "shadow", "reason": "Essence-Bound PC; shadow" },
    "fatima_ii":              { "element": "shadow", "reason": "Essence-Bound PC; shadow" },
    "fatima_iii":             { "element": "shadow", "reason": "Essence-Bound PC; shadow" },
    "king_in_yellow_i":       { "element": "arcane", "reason": "Dark Power sealed in the Amber Temple — an ancient arcane repository of forbidden knowledge" },
    "king_in_yellow_ii":      { "element": "arcane", "reason": "Dark Power sealed in the Amber Temple — an ancient arcane repository of forbidden knowledge" },
    "king_in_yellow_iii":     { "element": "arcane", "reason": "Dark Power sealed in the Amber Temple — an ancient arcane repository of forbidden knowledge" },
    "the_conquerer_i":        { "element": "arcane", "reason": "Dark Power sealed in the Amber Temple — an ancient arcane repository of forbidden knowledge" },
    "the_conquerer_ii":       { "element": "arcane", "reason": "Dark Power sealed in the Amber Temple — an ancient arcane repository of forbidden knowledge" },
    "the_conquerer_iii":      { "element": "arcane", "reason": "Dark Power sealed in the Amber Temple — an ancient arcane repository of forbidden knowledge" },
    "storm_shadow_i":         { "element": "shadow", "reason": "shadow dragon; shadow tag" },
    "storm_shadow_ii":        { "element": "shadow", "reason": "shadow dragon; shadow tag" },
    "storm_shadow_iii":       { "element": "shadow", "reason": "shadow dragon; shadow tag" }
  }
}
